{
  "Version": "2012-10-17",
  "Statement": [
    {
      "Sid": "CostExplorerRead",
      "Effect": "Allow",
      "Action": [
        "ce:GetCostAndUsage"
      ],
      "Resource": "*"
    },
    {
      "Sid": "EC2Read",
      "Effect": "Allow",
      "Action": [
        "ec2:DescribeInstances"
      ],
      "Resource": "*"
    },
    {
      "Sid": "CloudWatchRead",
      "Effect": "Allow",
      "Action": [
        "cloudwatch:DescribeAlarms"
      ],
      "Resource": "*"
    },
    {
      "Sid": "LambdaRead",
      "Effect": "Allow",
      "Action": [
        "lambda:ListFunctions"
      ],
      "Resource": "*"
    },
    {
      "Sid": "S3Read",
      "Effect": "Allow",
      "Action": [
        "s3:ListAllMyBuckets",
        "s3:GetBucketLocation",
        "s3:GetBucketPublicAccessBlock",
        "s3:GetBucketEncryption",
        "s3:GetBucketVersioning",
        "s3:GetLifecycleConfiguration",
        "s3:GetBucketPolicyStatus"
      ],
      "Resource": "*"
    },
    {
      "Sid": "ECRRead",
      "Effect": "Allow",
      "Action": [
        "ecr:DescribeImages",
        "ecr:DescribeImageScanFindings",
        "ecr:GetLifecyclePolicy"
      ],
      "Resource": "*"
    },
    {
      "Sid": "CloudWatchLogsRead",
      "Effect": "Allow",
      "Action": [
        "logs:DescribeLogGroups",
        "logs:FilterLogEvents",
        "logs:DescribeLogStreams"
      ],
      "Resource": "*"
    },
    {
      "Sid": "ECSRead",
      "Effect": "Allow",
      "Action": [
        "ecs:DescribeClusters",
        "ecs:DescribeServices",
        "ecs:ListTasks",
        "ecs:DescribeTasks",
        "ecs:DescribeTaskDefinition"
      ],
      "Resource": "*"
    },
    {
      "Sid": "RDSRead",
      "Effect": "Allow",
      "Action": [
        "rds:DescribeDBInstances",
        "rds:DescribeDBSubnetGroups"
      ],
      "Resource": "*"
    },
    {
      "Sid": "CloudWatchMetricsRead",
      "Effect": "Allow",
      "Action": [
        "cloudwatch:GetMetricData"
      ],
      "Resource": "*"
    },
    {
      "Sid": "SSMRead",
      "Effect": "Allow",
      "Action": [
        "ssm:DescribeParameters",
        "ssm:GetParameters"
      ],
      "Resource": "*"
    },
    {
      "Sid": "SesRead",
      "Effect": "Allow",
      "Action": [
        "ses:GetConfigurationSet",
        "ses:GetConfigurationSetEventDestinations"
      ],
      "Resource": "*"
    },
    {
      "Sid": "SnsRead",
      "Effect": "Allow",
      "Action": [
        "sns:ListTopics",
        "sns:GetTopicAttributes",
        "sns:ListSubscriptionsByTopic"
      ],
      "Resource": "*"
    },
    {
      "Sid": "EventBridgeRead",
      "Effect": "Allow",
      "Action": [
        "events:ListRules",
        "events:DescribeRule",
        "events:ListTargetsByRule"
      ],
      "Resource": "*"
    },
    {
      "Sid": "SchedulerRead",
      "Effect": "Allow",
      "Action": [
        "scheduler:ListSchedules",
        "scheduler:GetSchedule"
      ],
      "Resource": "*"
    },
    {
      "Sid": "BudgetsRead",
      "Effect": "Allow",
      "Action": [
        "budgets:DescribeBudgets",
        "budgets:DescribeNotificationsForBudget",
        "budgets:DescribeSubscribersForNotification"
      ],
      "Resource": "*"
    }
  ]
}
